rizk/__init__.py
rizk/sdk/__init__.py
rizk/sdk/_di_container.py
rizk/sdk/_lazy_imports.py
rizk/sdk/adapters/__init__.py
rizk/sdk/adapters/agents_adapter.py
rizk/sdk/adapters/anthropic_adapter.py
rizk/sdk/adapters/base.py
rizk/sdk/adapters/crew_ai.py
rizk/sdk/adapters/framework_adapter.py
rizk/sdk/adapters/gemini_adapter.py
rizk/sdk/adapters/guardrail_adapter.py
rizk/sdk/adapters/langchain.py
rizk/sdk/adapters/langgraph_adapter.py
rizk/sdk/adapters/llama_index.py
rizk/sdk/adapters/llm_base_adapter.py
rizk/sdk/adapters/ollama_adapter.py
rizk/sdk/adapters/openai_agents_adapter.py
rizk/sdk/adapters/openai_completion_adapter.py
rizk/sdk/adapters/openai_responses_adapter.py
rizk/sdk/analytics/__init__.py
rizk/sdk/analytics/processors.py
rizk/sdk/cache/__init__.py
rizk/sdk/cache/cache_hierarchy.py
rizk/sdk/cache/redis_adapter.py
rizk/sdk/client/__init__.py
rizk/sdk/client/client.py
rizk/sdk/config.py
rizk/sdk/decorators/__init__.py
rizk/sdk/decorators/base.py
rizk/sdk/decorators/guardrails.py
rizk/sdk/decorators/mcp_guardrails.py
rizk/sdk/decorators/policies.py
rizk/sdk/guardrails/_service_locator.py
rizk/sdk/guardrails/augmentation.py
rizk/sdk/guardrails/decision.py
rizk/sdk/guardrails/default_policies.yaml
rizk/sdk/guardrails/engine.py
rizk/sdk/guardrails/fast_rules.py
rizk/sdk/guardrails/llm_fallback.py
rizk/sdk/guardrails/llm_service.py
rizk/sdk/guardrails/policy_augmentation.py
rizk/sdk/guardrails/state_manager.py
rizk/sdk/guardrails/types.py
rizk/sdk/performance/__init__.py
rizk/sdk/plugins/__init__.py
rizk/sdk/plugins/discovery.py
rizk/sdk/plugins/manager.py
rizk/sdk/py.typed
rizk/sdk/streaming/__init__.py
rizk/sdk/streaming/stream_adapters.py
rizk/sdk/streaming/stream_cache.py
rizk/sdk/streaming/stream_guardrails.py
rizk/sdk/streaming/stream_processor.py
rizk/sdk/streaming/types.py
rizk/sdk/telemetry.py
rizk/sdk/tracing/__init__.py
rizk/sdk/tracing/tracing.py
rizk/sdk/types.py
rizk/sdk/utils/__init__.py
rizk/sdk/utils/cache_manager.py
rizk-0.5.0.dist-info/LICENSE
rizk-0.5.0.dist-info/METADATA
rizk-0.5.0.dist-info/NOTICE
rizk-0.5.0.dist-info/WHEEL
rizk-0.5.0.dist-info/RECORD
