Metadata-Version: 2.3
Name: rizk
Version: 0.5.0
Summary: Rizk SDK for LLM observability and policy enforcement
License: Apache-2.0
Keywords: llm,observability,policy,governance,tracing,opentelemetry
Author: Rizk Team
Author-email: hello@rizk.tools
Requires-Python: >=3.10,<4
Classifier: Development Status :: 3 - Alpha
Classifier: Intended Audience :: Developers
Classifier: License :: OSI Approved :: Apache Software License
Classifier: Programming Language :: Python :: 3
Classifier: Programming Language :: Python :: 3.10
Classifier: Programming Language :: Python :: 3.11
Classifier: Programming Language :: Python :: 3.12
Classifier: Programming Language :: Python :: 3.13
Classifier: Topic :: Software Development :: Libraries :: Python Modules
Requires-Dist: colorama (>=0.4.6,<0.5.0)
Requires-Dist: opentelemetry-api (>=1.28.0,<2.0.0)
Requires-Dist: opentelemetry-exporter-otlp-proto-grpc (>=1.28.0,<2.0.0)
Requires-Dist: opentelemetry-exporter-otlp-proto-http (>=1.28.0,<2.0.0)
Requires-Dist: opentelemetry-sdk (>=1.28.0,<2.0.0)
Requires-Dist: pydantic (>=1)
Requires-Dist: traceloop-sdk (>=0.38.12)
Project-URL: Documentation, https://docs.rizk.tools
Project-URL: Repository, https://github.com/rizk-tools/rizk-sdk
